cbstools/Jama-mipav.jar
cbstools/__init__.py
cbstools/_cbstools.so
cbstools/cbstools-lib.jar
cbstools/cbstools.jar
cbstools/commons-math3-3.5.jar
nighres/__init__.py
nighres/global_settings.py
nighres/utils.py
nighres/atlases/brain-segmentation-prior3.0/atlas_amygdalaL.raw
nighres/atlases/brain-segmentation-prior3.0/atlas_amygdalaL.xml
nighres/atlases/brain-segmentation-prior3.0/atlas_amygdalaR.raw
nighres/atlases/brain-segmentation-prior3.0/atlas_amygdalaR.xml
nighres/atlases/brain-segmentation-prior3.0/atlas_arteries.raw
nighres/atlases/brain-segmentation-prior3.0/atlas_arteries.xml
nighres/atlases/brain-segmentation-prior3.0/atlas_background.raw
nighres/atlases/brain-segmentation-prior3.0/atlas_background.xml
nighres/atlases/brain-segmentation-prior3.0/atlas_brainstem.raw
nighres/atlases/brain-segmentation-prior3.0/atlas_brainstem.xml
nighres/atlases/brain-segmentation-prior3.0/atlas_caudateL.raw
nighres/atlases/brain-segmentation-prior3.0/atlas_caudateL.xml
nighres/atlases/brain-segmentation-prior3.0/atlas_caudateR.raw
nighres/atlases/brain-segmentation-prior3.0/atlas_caudateR.xml
nighres/atlases/brain-segmentation-prior3.0/atlas_cerebellum_gm.raw
nighres/atlases/brain-segmentation-prior3.0/atlas_cerebellum_gm.xml
nighres/atlases/brain-segmentation-prior3.0/atlas_cerebellum_wm.raw
nighres/atlases/brain-segmentation-prior3.0/atlas_cerebellum_wm.xml
nighres/atlases/brain-segmentation-prior3.0/atlas_cerebrum_gmL.raw
nighres/atlases/brain-segmentation-prior3.0/atlas_cerebrum_gmL.xml
nighres/atlases/brain-segmentation-prior3.0/atlas_cerebrum_gmR.raw
nighres/atlases/brain-segmentation-prior3.0/atlas_cerebrum_gmR.xml
nighres/atlases/brain-segmentation-prior3.0/atlas_cerebrum_wmL.raw
nighres/atlases/brain-segmentation-prior3.0/atlas_cerebrum_wmL.xml
nighres/atlases/brain-segmentation-prior3.0/atlas_cerebrum_wmR.raw
nighres/atlases/brain-segmentation-prior3.0/atlas_cerebrum_wmR.xml
nighres-1.0.0b4.dist-info/DESCRIPTION.rst
nighres-1.0.0b4.dist-info/METADATA
nighres-1.0.0b4.dist-info/RECORD
nighres-1.0.0b4.dist-info/WHEEL
nighres-1.0.0b4.dist-info/metadata.json
nighres-1.0.0b4.dist-info/top_level.txt
