Metadata-Version: 2.0
Name: nighres
Version: 1.0.0b4
Summary: Processing tools for high-resolution neuroimaging
Home-page: https://nighres.readthedocs.io/
Author: Julia M Huntenburg, Pierre-Louis Bazin, Chris Steele
Author-email: ju.huntenburg@gmail.com
License: Apache License, 2.0
Keywords: MRI high-resolution laminar
Platform: UNKNOWN
Classifier: Development Status :: 4 - Beta
Classifier: Topic :: Scientific/Engineering
Classifier: Intended Audience :: Science/Research
Classifier: License :: OSI Approved :: Apache Software License
Classifier: Programming Language :: Python :: 2.7
Requires-Dist: nibabel
Requires-Dist: numpy
